optlite/__init__.py
optlite/_version.py
optlite/pg_encoder.py
optlite/pg_logger.py
optlite-0.0.3.dist-info/METADATA
optlite-0.0.3.dist-info/WHEEL
optlite-0.0.3.dist-info/top_level.txt
optlite-0.0.3.dist-info/RECORD
