Metadata-Version: 2.1
Name: optlite
Version: 0.0.3
Summary: Serverless setup for OPT with pyodide.
Home-page: https://github.com/dive4dec/optlite
Author: DIVE
Author-email: chungc@alum.mit.edu
License: BSD
Platform: Linux
Platform: Mac OS X
Platform: Windows
Classifier: Intended Audience :: Education
Classifier: Intended Audience :: Developers
Classifier: Intended Audience :: Science/Research
Classifier: License :: OSI Approved :: BSD License
Classifier: Programming Language :: Python
Requires-Python: >=3.6
